pygments_solarized/__init__.py
pygments_solarized/dark.py
pygments_solarized/dark256.py
pygments_solarized/light.py
pygments_solarized-0.0.3.dist-info/DESCRIPTION.rst
pygments_solarized-0.0.3.dist-info/METADATA
pygments_solarized-0.0.3.dist-info/RECORD
pygments_solarized-0.0.3.dist-info/WHEEL
pygments_solarized-0.0.3.dist-info/entry_points.txt
pygments_solarized-0.0.3.dist-info/metadata.json
pygments_solarized-0.0.3.dist-info/top_level.txt
